ydt/__init__.py
ydt/auto_label/__init__.py
ydt/auto_label/core.py
ydt/auto_label/model_utils.py
ydt/auto_label/structure.py
ydt/cli/__init__.py
ydt/cli/__main__.py
ydt/cli/main.py
ydt/core/__init__.py
ydt/core/formats.py
ydt/core/logger.py
ydt/core/utils.py
ydt/dataset/__init__.py
ydt/dataset/split.py
ydt/dataset/synthesize.py
ydt/image/__init__.py
ydt/image/augment.py
ydt/image/concat.py
ydt/image/resize.py
ydt/image/slice.py
ydt/image/video.py
ydt/visual/__init__.py
ydt/visual/augment.py
ydt/visual/dataset.py
ydt/visual/letter.py
yolodt-0.2.7.dist-info/METADATA
yolodt-0.2.7.dist-info/WHEEL
yolodt-0.2.7.dist-info/entry_points.txt
yolodt-0.2.7.dist-info/licenses/LICENSE
yolodt-0.2.7.dist-info/RECORD
