Metadata-Version: 2.4
Name: yolodt
Version: 0.2.7
Summary: YOLO Dataset Tools - Comprehensive toolkit for YOLO format dataset processing
Project-URL: Homepage, https://github.com/jaffe-fly/ydt
Project-URL: Repository, https://github.com/jaffe-fly/ydt
Project-URL: Issues, https://github.com/jaffe-fly/ydt/issues
Author: YDT Contributors
License: MIT
License-File: LICENSE
Keywords: computer-vision,dataset,image-processing,obb,object-detection,yolo
Classifier: Development Status :: 3 - Alpha
Classifier: Intended Audience :: Developers
Classifier: Intended Audience :: Science/Research
Classifier: License :: OSI Approved :: MIT License
Classifier: Programming Language :: Python :: 3
Classifier: Programming Language :: Python :: 3.10
Classifier: Programming Language :: Python :: 3.11
Classifier: Programming Language :: Python :: 3.12
Classifier: Topic :: Scientific/Engineering :: Artificial Intelligence
Classifier: Topic :: Scientific/Engineering :: Image Processing
Requires-Python: >=3.10
Requires-Dist: albumentations>=1.3.0
Requires-Dist: imagehash>=4.3.0
Requires-Dist: minio>=7.0.0
Requires-Dist: numpy>=1.20.0
Requires-Dist: opencv-python>=4.5.0
Requires-Dist: pillow>=8.0.0
Requires-Dist: pyyaml>=5.4.0
Requires-Dist: sahi>=0.11.0
Requires-Dist: scikit-learn>=1.0.0
Requires-Dist: tqdm>=4.60.0
Requires-Dist: ultralytics>=8.0.0
Provides-Extra: dev
Requires-Dist: pytest-cov>=3.0.0; extra == 'dev'
Requires-Dist: pytest>=7.0.0; extra == 'dev'
Requires-Dist: ruff>=0.14.0; extra == 'dev'
